epitoolkit/__init__.py
epitoolkit/exceptions.py
epitoolkit/tools.py
epitoolkit/utils.py
epitoolkit/validators.py
epitoolkit-0.2.6.dist-info/LICENSE
epitoolkit-0.2.6.dist-info/WHEEL
epitoolkit-0.2.6.dist-info/METADATA
epitoolkit-0.2.6.dist-info/RECORD
