Metadata-Version: 2.1
Name: epitoolkit
Version: 0.2.6
Summary: EpiToolkit is a set of tools useful in the analysis of data from EPIC / 450K microarrays.
Home-page: https://github.com/ClinicalEpigeneticsLaboratory/EpiGenToolKit
License: MIT
Author: Jan Bińkowski
Author-email: jan.binkowski@pum.edu.pl
Requires-Python: >=3.8,<3.10
Classifier: License :: OSI Approved :: MIT License
Classifier: Programming Language :: Python :: 3
Classifier: Programming Language :: Python :: 3.8
Classifier: Programming Language :: Python :: 3.9
Requires-Dist: Sphinx (>=4.2.0,<5.0.0)
Requires-Dist: autopep8 (>=1.5.7,<2.0.0)
Requires-Dist: matplotlib (>=3.4.3,<4.0.0)
Requires-Dist: numpy (>=1.21.3,<2.0.0)
Requires-Dist: pandas (>=1.3.4,<2.0.0)
Requires-Dist: pathlib (>=1.0.1,<2.0.0)
Requires-Dist: plotly (>=5.3.1,<6.0.0)
Requires-Dist: scipy (>=1.7.1,<2.0.0)
Requires-Dist: seaborn (>=0.11.2,<0.12.0)
Requires-Dist: tqdm (>=4.62.3,<5.0.0)
Project-URL: Repository, https://github.com/ClinicalEpigeneticsLaboratory/EpiGenToolKit
